cpn_cli/__init__.py
cpn_cli/__main__.py
cpn_cli/constants.py
cpn_cli/models/apis_settings.py
cpn_cli/models/config.py
cpn_cli/models/etraffic_settings.py
cpn_cli/models/notifcations/base.py
cpn_cli/models/notifcations/discord.py
cpn_cli/models/notifcations/telegram.py
cpn_cli/modules/argparse.py
cpn_cli/modules/config_reader.py
cpn_cli/modules/get_data.py
cpn_cli/modules/notify.py
cpn_cli/modules/print_console.py
cpn_cli/modules/setup_logger.py
cpn_cli-0.5.0.dist-info/METADATA
cpn_cli-0.5.0.dist-info/WHEEL
cpn_cli-0.5.0.dist-info/entry_points.txt
cpn_cli-0.5.0.dist-info/licenses/LICENSE
cpn_cli-0.5.0.dist-info/RECORD
